szcore_evaluation/__init__.py
szcore_evaluation/__main__.py
szcore_evaluation/evaluate.py
szcore_evaluation-0.0.7.dist-info/METADATA
szcore_evaluation-0.0.7.dist-info/WHEEL
szcore_evaluation-0.0.7.dist-info/RECORD
