Metadata-Version: 2.4
Name: szcore-evaluation
Version: 0.0.7
Summary: Compare szCORE compliant annotations of EEG datasets of people with epilelpsy.
Author-email: Jonathan Dan <jonathan.dan@epfl.ch>
Requires-Python: >=3.12
Requires-Dist: epilepsy2bids>=0.0.7
Requires-Dist: numpy>=1.26.4
Requires-Dist: timescoring>=0.0.5
